presspy/__init__.py
presspy/cli.py
presspy/press.py
presspy-1.0.0.dist-info/LICENSE
presspy-1.0.0.dist-info/METADATA
presspy-1.0.0.dist-info/WHEEL
presspy-1.0.0.dist-info/entry_points.txt
presspy-1.0.0.dist-info/top_level.txt
presspy-1.0.0.dist-info/RECORD
