Metadata-Version: 2.1
Name: presspy
Version: 1.0.0
Summary: A Python Compression Software
Home-page: https://github.com/BD103/PressPy
Author: BD103
Author-email: dont@stalk.me
License: UNKNOWN
Platform: UNKNOWN
Classifier: Programming Language :: Python :: 3
Classifier: License :: OSI Approved :: Apache Software License
Classifier: Operating System :: OS Independent
Classifier: Development Status :: 1 - Planning
Requires-Python: >=3.7
Requires-Dist: click
